[
    {
        "beginLineNum": 53,
        "lastUsedLineNum": 66,
        "name": "crc"
    },
    {
        "beginLineNum": 797,
        "lastUsedLineNum": 1079,
        "name": "i"
    },
    {
        "beginLineNum": 797,
        "lastUsedLineNum": 1079,
        "name": "j"
    },
    {
        "beginLineNum": 797,
        "lastUsedLineNum": 1060,
        "name": "k"
    },
    {
        "beginLineNum": 209,
        "lastUsedLineNum": 212,
        "name": "l_10"
    },
    {
        "beginLineNum": 653,
        "lastUsedLineNum": 658,
        "name": "l_1007"
    },
    {
        "beginLineNum": 576,
        "lastUsedLineNum": 668,
        "name": "l_1008"
    },
    {
        "beginLineNum": 639,
        "lastUsedLineNum": 659,
        "name": "l_1009"
    },
    {
        "beginLineNum": 577,
        "lastUsedLineNum": 703,
        "name": "l_1012"
    },
    {
        "beginLineNum": 640,
        "lastUsedLineNum": 659,
        "name": "l_1016"
    },
    {
        "beginLineNum": 635,
        "lastUsedLineNum": 659,
        "name": "l_1024"
    },
    {
        "beginLineNum": 631,
        "lastUsedLineNum": 668,
        "name": "l_1039"
    },
    {
        "beginLineNum": 666,
        "lastUsedLineNum": 668,
        "name": "l_1040"
    },
    {
        "beginLineNum": 604,
        "lastUsedLineNum": 670,
        "name": "l_1041"
    },
    {
        "beginLineNum": 603,
        "lastUsedLineNum": 610,
        "name": "l_1042"
    },
    {
        "beginLineNum": 578,
        "lastUsedLineNum": 705,
        "name": "l_1045"
    },
    {
        "beginLineNum": 605,
        "lastUsedLineNum": 671,
        "name": "l_1047"
    },
    {
        "beginLineNum": 606,
        "lastUsedLineNum": 691,
        "name": "l_1052"
    },
    {
        "beginLineNum": 675,
        "lastUsedLineNum": 691,
        "name": "l_1053"
    },
    {
        "beginLineNum": 684,
        "lastUsedLineNum": 691,
        "name": "l_1069"
    },
    {
        "beginLineNum": 686,
        "lastUsedLineNum": 691,
        "name": "l_1071"
    },
    {
        "beginLineNum": 689,
        "lastUsedLineNum": 691,
        "name": "l_1077"
    },
    {
        "beginLineNum": 585,
        "lastUsedLineNum": 694,
        "name": "l_1083"
    },
    {
        "beginLineNum": 587,
        "lastUsedLineNum": 694,
        "name": "l_1084"
    },
    {
        "beginLineNum": 586,
        "lastUsedLineNum": 587,
        "name": "l_1085"
    },
    {
        "beginLineNum": 700,
        "lastUsedLineNum": 705,
        "name": "l_1099"
    },
    {
        "beginLineNum": 208,
        "lastUsedLineNum": 209,
        "name": "l_11"
    },
    {
        "beginLineNum": 701,
        "lastUsedLineNum": 705,
        "name": "l_1100"
    },
    {
        "beginLineNum": 702,
        "lastUsedLineNum": 705,
        "name": "l_1101"
    },
    {
        "beginLineNum": 703,
        "lastUsedLineNum": 705,
        "name": "l_1102"
    },
    {
        "beginLineNum": 556,
        "lastUsedLineNum": 560,
        "name": "l_1122"
    },
    {
        "beginLineNum": 557,
        "lastUsedLineNum": 560,
        "name": "l_1123"
    },
    {
        "beginLineNum": 279,
        "lastUsedLineNum": 283,
        "name": "l_1128"
    },
    {
        "beginLineNum": 280,
        "lastUsedLineNum": 283,
        "name": "l_1129"
    },
    {
        "beginLineNum": 295,
        "lastUsedLineNum": 334,
        "name": "l_1141"
    },
    {
        "beginLineNum": 298,
        "lastUsedLineNum": 483,
        "name": "l_1146"
    },
    {
        "beginLineNum": 297,
        "lastUsedLineNum": 534,
        "name": "l_1147"
    },
    {
        "beginLineNum": 296,
        "lastUsedLineNum": 513,
        "name": "l_1148"
    },
    {
        "beginLineNum": 299,
        "lastUsedLineNum": 339,
        "name": "l_1149"
    },
    {
        "beginLineNum": 300,
        "lastUsedLineNum": 425,
        "name": "l_1151"
    },
    {
        "beginLineNum": 301,
        "lastUsedLineNum": 425,
        "name": "l_1152"
    },
    {
        "beginLineNum": 302,
        "lastUsedLineNum": 503,
        "name": "l_1153"
    },
    {
        "beginLineNum": 303,
        "lastUsedLineNum": 442,
        "name": "l_1154"
    },
    {
        "beginLineNum": 304,
        "lastUsedLineNum": 334,
        "name": "l_1155"
    },
    {
        "beginLineNum": 744,
        "lastUsedLineNum": 752,
        "name": "l_116"
    },
    {
        "beginLineNum": 336,
        "lastUsedLineNum": 394,
        "name": "l_1162"
    },
    {
        "beginLineNum": 305,
        "lastUsedLineNum": 521,
        "name": "l_1163"
    },
    {
        "beginLineNum": 337,
        "lastUsedLineNum": 374,
        "name": "l_1165"
    },
    {
        "beginLineNum": 306,
        "lastUsedLineNum": 521,
        "name": "l_1166"
    },
    {
        "beginLineNum": 340,
        "lastUsedLineNum": 357,
        "name": "l_1167"
    },
    {
        "beginLineNum": 339,
        "lastUsedLineNum": 353,
        "name": "l_1168"
    },
    {
        "beginLineNum": 342,
        "lastUsedLineNum": 379,
        "name": "l_1169"
    },
    {
        "beginLineNum": 341,
        "lastUsedLineNum": 408,
        "name": "l_1170"
    },
    {
        "beginLineNum": 307,
        "lastUsedLineNum": 487,
        "name": "l_1174"
    },
    {
        "beginLineNum": 343,
        "lastUsedLineNum": 399,
        "name": "l_1175"
    },
    {
        "beginLineNum": 344,
        "lastUsedLineNum": 353,
        "name": "l_1176"
    },
    {
        "beginLineNum": 345,
        "lastUsedLineNum": 408,
        "name": "l_1177"
    },
    {
        "beginLineNum": 371,
        "lastUsedLineNum": 374,
        "name": "l_1179"
    },
    {
        "beginLineNum": 308,
        "lastUsedLineNum": 374,
        "name": "l_1187"
    },
    {
        "beginLineNum": 372,
        "lastUsedLineNum": 374,
        "name": "l_1188"
    },
    {
        "beginLineNum": 355,
        "lastUsedLineNum": 374,
        "name": "l_1189"
    },
    {
        "beginLineNum": 356,
        "lastUsedLineNum": 399,
        "name": "l_1190"
    },
    {
        "beginLineNum": 378,
        "lastUsedLineNum": 398,
        "name": "l_1191"
    },
    {
        "beginLineNum": 366,
        "lastUsedLineNum": 399,
        "name": "l_1194"
    },
    {
        "beginLineNum": 347,
        "lastUsedLineNum": 398,
        "name": "l_1197"
    },
    {
        "beginLineNum": 346,
        "lastUsedLineNum": 347,
        "name": "l_1198"
    },
    {
        "beginLineNum": 357,
        "lastUsedLineNum": 398,
        "name": "l_1203"
    },
    {
        "beginLineNum": 379,
        "lastUsedLineNum": 398,
        "name": "l_1204"
    },
    {
        "beginLineNum": 367,
        "lastUsedLineNum": 398,
        "name": "l_1205"
    },
    {
        "beginLineNum": 309,
        "lastUsedLineNum": 399,
        "name": "l_1219"
    },
    {
        "beginLineNum": 381,
        "lastUsedLineNum": 399,
        "name": "l_1220"
    },
    {
        "beginLineNum": 380,
        "lastUsedLineNum": 399,
        "name": "l_1221"
    },
    {
        "beginLineNum": 368,
        "lastUsedLineNum": 399,
        "name": "l_1222"
    },
    {
        "beginLineNum": 348,
        "lastUsedLineNum": 399,
        "name": "l_1225"
    },
    {
        "beginLineNum": 383,
        "lastUsedLineNum": 399,
        "name": "l_1232"
    },
    {
        "beginLineNum": 384,
        "lastUsedLineNum": 399,
        "name": "l_1233"
    },
    {
        "beginLineNum": 358,
        "lastUsedLineNum": 399,
        "name": "l_1234"
    },
    {
        "beginLineNum": 361,
        "lastUsedLineNum": 403,
        "name": "l_1245"
    },
    {
        "beginLineNum": 362,
        "lastUsedLineNum": 403,
        "name": "l_1246"
    },
    {
        "beginLineNum": 349,
        "lastUsedLineNum": 408,
        "name": "l_1251"
    },
    {
        "beginLineNum": 312,
        "lastUsedLineNum": 483,
        "name": "l_1252"
    },
    {
        "beginLineNum": 311,
        "lastUsedLineNum": 312,
        "name": "l_1253"
    },
    {
        "beginLineNum": 310,
        "lastUsedLineNum": 427,
        "name": "l_1254"
    },
    {
        "beginLineNum": 407,
        "lastUsedLineNum": 408,
        "name": "l_1255"
    },
    {
        "beginLineNum": 423,
        "lastUsedLineNum": 528,
        "name": "l_1260"
    },
    {
        "beginLineNum": 424,
        "lastUsedLineNum": 513,
        "name": "l_1261"
    },
    {
        "beginLineNum": 425,
        "lastUsedLineNum": 482,
        "name": "l_1262"
    },
    {
        "beginLineNum": 313,
        "lastUsedLineNum": 330,
        "name": "l_1263"
    },
    {
        "beginLineNum": 314,
        "lastUsedLineNum": 330,
        "name": "l_1264"
    },
    {
        "beginLineNum": 315,
        "lastUsedLineNum": 532,
        "name": "l_1265"
    },
    {
        "beginLineNum": 316,
        "lastUsedLineNum": 326,
        "name": "l_1266"
    },
    {
        "beginLineNum": 318,
        "lastUsedLineNum": 435,
        "name": "l_1269"
    },
    {
        "beginLineNum": 438,
        "lastUsedLineNum": 453,
        "name": "l_1278"
    },
    {
        "beginLineNum": 439,
        "lastUsedLineNum": 454,
        "name": "l_1279"
    },
    {
        "beginLineNum": 449,
        "lastUsedLineNum": 463,
        "name": "l_1280"
    },
    {
        "beginLineNum": 450,
        "lastUsedLineNum": 462,
        "name": "l_1283"
    },
    {
        "beginLineNum": 440,
        "lastUsedLineNum": 470,
        "name": "l_1290"
    },
    {
        "beginLineNum": 459,
        "lastUsedLineNum": 463,
        "name": "l_1293"
    },
    {
        "beginLineNum": 443,
        "lastUsedLineNum": 469,
        "name": "l_1295"
    },
    {
        "beginLineNum": 442,
        "lastUsedLineNum": 443,
        "name": "l_1296"
    },
    {
        "beginLineNum": 472,
        "lastUsedLineNum": 476,
        "name": "l_1301"
    },
    {
        "beginLineNum": 473,
        "lastUsedLineNum": 484,
        "name": "l_1310"
    },
    {
        "beginLineNum": 478,
        "lastUsedLineNum": 483,
        "name": "l_1311"
    },
    {
        "beginLineNum": 444,
        "lastUsedLineNum": 483,
        "name": "l_1312"
    },
    {
        "beginLineNum": 479,
        "lastUsedLineNum": 483,
        "name": "l_1313"
    },
    {
        "beginLineNum": 429,
        "lastUsedLineNum": 483,
        "name": "l_1316"
    },
    {
        "beginLineNum": 428,
        "lastUsedLineNum": 429,
        "name": "l_1317"
    },
    {
        "beginLineNum": 427,
        "lastUsedLineNum": 428,
        "name": "l_1318"
    },
    {
        "beginLineNum": 474,
        "lastUsedLineNum": 483,
        "name": "l_1319"
    },
    {
        "beginLineNum": 319,
        "lastUsedLineNum": 483,
        "name": "l_1320"
    },
    {
        "beginLineNum": 486,
        "lastUsedLineNum": 490,
        "name": "l_1325"
    },
    {
        "beginLineNum": 480,
        "lastUsedLineNum": 490,
        "name": "l_1326"
    },
    {
        "beginLineNum": 481,
        "lastUsedLineNum": 490,
        "name": "l_1328"
    },
    {
        "beginLineNum": 487,
        "lastUsedLineNum": 490,
        "name": "l_1329"
    },
    {
        "beginLineNum": 445,
        "lastUsedLineNum": 491,
        "name": "l_1330"
    },
    {
        "beginLineNum": 475,
        "lastUsedLineNum": 496,
        "name": "l_1331"
    },
    {
        "beginLineNum": 430,
        "lastUsedLineNum": 500,
        "name": "l_1334"
    },
    {
        "beginLineNum": 502,
        "lastUsedLineNum": 505,
        "name": "l_1336"
    },
    {
        "beginLineNum": 509,
        "lastUsedLineNum": 512,
        "name": "l_1337"
    },
    {
        "beginLineNum": 431,
        "lastUsedLineNum": 514,
        "name": "l_1342"
    },
    {
        "beginLineNum": 432,
        "lastUsedLineNum": 528,
        "name": "l_1348"
    },
    {
        "beginLineNum": 521,
        "lastUsedLineNum": 528,
        "name": "l_1349"
    },
    {
        "beginLineNum": 524,
        "lastUsedLineNum": 528,
        "name": "l_1352"
    },
    {
        "beginLineNum": 525,
        "lastUsedLineNum": 528,
        "name": "l_1355"
    },
    {
        "beginLineNum": 526,
        "lastUsedLineNum": 528,
        "name": "l_1359"
    },
    {
        "beginLineNum": 511,
        "lastUsedLineNum": 528,
        "name": "l_1362"
    },
    {
        "beginLineNum": 324,
        "lastUsedLineNum": 532,
        "name": "l_1363"
    },
    {
        "beginLineNum": 323,
        "lastUsedLineNum": 324,
        "name": "l_1364"
    },
    {
        "beginLineNum": 332,
        "lastUsedLineNum": 533,
        "name": "l_1372"
    },
    {
        "beginLineNum": 255,
        "lastUsedLineNum": 260,
        "name": "l_1378"
    },
    {
        "beginLineNum": 257,
        "lastUsedLineNum": 260,
        "name": "l_1380"
    },
    {
        "beginLineNum": 175,
        "lastUsedLineNum": 214,
        "name": "l_1382"
    },
    {
        "beginLineNum": 235,
        "lastUsedLineNum": 240,
        "name": "l_1385"
    },
    {
        "beginLineNum": 185,
        "lastUsedLineNum": 214,
        "name": "l_1398"
    },
    {
        "beginLineNum": 199,
        "lastUsedLineNum": 214,
        "name": "l_1407"
    },
    {
        "beginLineNum": 200,
        "lastUsedLineNum": 214,
        "name": "l_1408"
    },
    {
        "beginLineNum": 201,
        "lastUsedLineNum": 214,
        "name": "l_1409"
    },
    {
        "beginLineNum": 202,
        "lastUsedLineNum": 205,
        "name": "l_1410"
    },
    {
        "beginLineNum": 176,
        "lastUsedLineNum": 214,
        "name": "l_1411"
    },
    {
        "beginLineNum": 186,
        "lastUsedLineNum": 217,
        "name": "l_1414"
    },
    {
        "beginLineNum": 178,
        "lastUsedLineNum": 221,
        "name": "l_1425"
    },
    {
        "beginLineNum": 193,
        "lastUsedLineNum": 222,
        "name": "l_1428"
    },
    {
        "beginLineNum": 745,
        "lastUsedLineNum": 770,
        "name": "l_184"
    },
    {
        "beginLineNum": 748,
        "lastUsedLineNum": 749,
        "name": "l_237"
    },
    {
        "beginLineNum": 198,
        "lastUsedLineNum": 214,
        "name": "l_24"
    },
    {
        "beginLineNum": 174,
        "lastUsedLineNum": 224,
        "name": "l_25"
    },
    {
        "beginLineNum": 184,
        "lastUsedLineNum": 214,
        "name": "l_26"
    },
    {
        "beginLineNum": 251,
        "lastUsedLineNum": 260,
        "name": "l_27"
    },
    {
        "beginLineNum": 252,
        "lastUsedLineNum": 260,
        "name": "l_29"
    },
    {
        "beginLineNum": 254,
        "lastUsedLineNum": 259,
        "name": "l_31"
    },
    {
        "beginLineNum": 272,
        "lastUsedLineNum": 282,
        "name": "l_41"
    },
    {
        "beginLineNum": 274,
        "lastUsedLineNum": 283,
        "name": "l_46"
    },
    {
        "beginLineNum": 273,
        "lastUsedLineNum": 282,
        "name": "l_47"
    },
    {
        "beginLineNum": 275,
        "lastUsedLineNum": 282,
        "name": "l_54"
    },
    {
        "beginLineNum": 276,
        "lastUsedLineNum": 282,
        "name": "l_55"
    },
    {
        "beginLineNum": 546,
        "lastUsedLineNum": 559,
        "name": "l_71"
    },
    {
        "beginLineNum": 719,
        "lastUsedLineNum": 729,
        "name": "l_86"
    },
    {
        "beginLineNum": 718,
        "lastUsedLineNum": 729,
        "name": "l_87"
    },
    {
        "beginLineNum": 720,
        "lastUsedLineNum": 729,
        "name": "l_90"
    },
    {
        "beginLineNum": 721,
        "lastUsedLineNum": 729,
        "name": "l_91"
    },
    {
        "beginLineNum": 722,
        "lastUsedLineNum": 729,
        "name": "l_93"
    },
    {
        "beginLineNum": 725,
        "lastUsedLineNum": 729,
        "name": "l_930"
    },
    {
        "beginLineNum": 727,
        "lastUsedLineNum": 730,
        "name": "l_932"
    },
    {
        "beginLineNum": 547,
        "lastUsedLineNum": 559,
        "name": "l_933"
    },
    {
        "beginLineNum": 552,
        "lastUsedLineNum": 559,
        "name": "l_938"
    },
    {
        "beginLineNum": 551,
        "lastUsedLineNum": 552,
        "name": "l_939"
    },
    {
        "beginLineNum": 550,
        "lastUsedLineNum": 551,
        "name": "l_940"
    },
    {
        "beginLineNum": 549,
        "lastUsedLineNum": 550,
        "name": "l_941"
    },
    {
        "beginLineNum": 548,
        "lastUsedLineNum": 549,
        "name": "l_942"
    },
    {
        "beginLineNum": 591,
        "lastUsedLineNum": 611,
        "name": "l_949"
    },
    {
        "beginLineNum": 613,
        "lastUsedLineNum": 615,
        "name": "l_950"
    },
    {
        "beginLineNum": 619,
        "lastUsedLineNum": 622,
        "name": "l_953"
    },
    {
        "beginLineNum": 592,
        "lastUsedLineNum": 656,
        "name": "l_954"
    },
    {
        "beginLineNum": 572,
        "lastUsedLineNum": 650,
        "name": "l_960"
    },
    {
        "beginLineNum": 593,
        "lastUsedLineNum": 691,
        "name": "l_961"
    },
    {
        "beginLineNum": 594,
        "lastUsedLineNum": 629,
        "name": "l_962"
    },
    {
        "beginLineNum": 595,
        "lastUsedLineNum": 629,
        "name": "l_965"
    },
    {
        "beginLineNum": 573,
        "lastUsedLineNum": 702,
        "name": "l_969"
    },
    {
        "beginLineNum": 596,
        "lastUsedLineNum": 668,
        "name": "l_970"
    },
    {
        "beginLineNum": 597,
        "lastUsedLineNum": 691,
        "name": "l_971"
    },
    {
        "beginLineNum": 598,
        "lastUsedLineNum": 668,
        "name": "l_981"
    },
    {
        "beginLineNum": 599,
        "lastUsedLineNum": 629,
        "name": "l_982"
    },
    {
        "beginLineNum": 600,
        "lastUsedLineNum": 668,
        "name": "l_984"
    },
    {
        "beginLineNum": 602,
        "lastUsedLineNum": 629,
        "name": "l_985"
    },
    {
        "beginLineNum": 601,
        "lastUsedLineNum": 602,
        "name": "l_986"
    },
    {
        "beginLineNum": 575,
        "lastUsedLineNum": 694,
        "name": "l_987"
    },
    {
        "beginLineNum": 574,
        "lastUsedLineNum": 640,
        "name": "l_988"
    },
    {
        "beginLineNum": 723,
        "lastUsedLineNum": 729,
        "name": "l_99"
    },
    {
        "beginLineNum": 634,
        "lastUsedLineNum": 658,
        "name": "l_999"
    },
    {
        "beginLineNum": 54,
        "lastUsedLineNum": 61,
        "name": "poly"
    },
    {
        "beginLineNum": 798,
        "lastUsedLineNum": 1085,
        "name": "print_hash_value"
    }
]
